jupyter_deepagents/__init__.py
jupyter_deepagents/_version.py
jupyter_deepagents/agent_wrapper.py
jupyter_deepagents/handlers.py
jupyter_deepagents/labextension/package.json
jupyter_deepagents/labextension/schemas/jupyter-deepagents/package.json.orig
jupyter_deepagents/labextension/static/38.2cca873e4905a0875425.js
jupyter_deepagents/labextension/static/38.2cca873e4905a0875425.js.LICENSE.txt
jupyter_deepagents/labextension/static/728.853eae5cd486a66a713a.js
jupyter_deepagents/labextension/static/777.d3121cae1b4c137d8bec.js
jupyter_deepagents/labextension/static/remoteEntry.af24c85889bebb318400.js
jupyter_deepagents/labextension/static/style.js
jupyter_deepagents/labextension/static/third-party-licenses.json
jupyter_deepagents-0.1.0.data/data/etc/jupyter/jupyter_server_config.d/jupyter_deepagents.json
jupyter_deepagents-0.1.0.data/data/share/jupyter/labextensions/jupyter-deepagents/package.json
jupyter_deepagents-0.1.0.data/data/share/jupyter/labextensions/jupyter-deepagents/schemas/jupyter-deepagents/package.json.orig
jupyter_deepagents-0.1.0.data/data/share/jupyter/labextensions/jupyter-deepagents/static/38.2cca873e4905a0875425.js
jupyter_deepagents-0.1.0.data/data/share/jupyter/labextensions/jupyter-deepagents/static/38.2cca873e4905a0875425.js.LICENSE.txt
jupyter_deepagents-0.1.0.data/data/share/jupyter/labextensions/jupyter-deepagents/static/728.853eae5cd486a66a713a.js
jupyter_deepagents-0.1.0.data/data/share/jupyter/labextensions/jupyter-deepagents/static/777.d3121cae1b4c137d8bec.js
jupyter_deepagents-0.1.0.data/data/share/jupyter/labextensions/jupyter-deepagents/static/remoteEntry.af24c85889bebb318400.js
jupyter_deepagents-0.1.0.data/data/share/jupyter/labextensions/jupyter-deepagents/static/style.js
jupyter_deepagents-0.1.0.data/data/share/jupyter/labextensions/jupyter-deepagents/static/third-party-licenses.json
jupyter_deepagents-0.1.0.data/data/share/jupyter/labextensions/jupyter-deepagents/install.json
jupyter_deepagents-0.1.0.dist-info/METADATA
jupyter_deepagents-0.1.0.dist-info/WHEEL
jupyter_deepagents-0.1.0.dist-info/licenses/LICENSE
jupyter_deepagents-0.1.0.dist-info/RECORD
